voxdose_core/__init__.py
voxdose_core/analyze_wav_spl_f0.py
voxdose_core/dosi.py
voxdose_core/sp_cpps.py
voxdose_core/sp_pitch_praat.py
voxdose_core/sp_pitch_track_praat.py
voxdose_core/spl_fast.py
voxdose_core/spl_fast_c_th.py
voxdose_core/stima_livello.py
voxdose_gui/__init__.py
voxdose_gui/paths.py
voxdose_gui/splash.py
voxdose_gui/voxdose_app.py
voxdose_reports/__init__.py
voxdose_reports/analyze_plots.py
voxdose_reports/plots_pitch_block.py
voxdose_reports/plots_spl.py
voxdose_reports/plots_spl_block.py
voxdose_reports/plots_spl_dba.py
voxdose-1.0.0.dist-info/METADATA
voxdose-1.0.0.dist-info/WHEEL
voxdose-1.0.0.dist-info/entry_points.txt
voxdose-1.0.0.dist-info/top_level.txt
voxdose-1.0.0.dist-info/RECORD
