Metadata-Version: 2.4
Name: voxdose
Version: 1.0.0
Summary: Open-source vocal dose analyzer for voice professionals
Author-email: Tiago Lima Bicalho Cruz <fonotechacademy@gmail.com>
License: MIT
Project-URL: Homepage, https://github.com/tiagolbc/voxdose
Project-URL: Repository, https://github.com/tiagolbc/voxdose
Requires-Python: >=3.9
Requires-Dist: numpy
Requires-Dist: pandas
Requires-Dist: matplotlib
Requires-Dist: soundfile
Requires-Dist: PySide6
Requires-Dist: openpyxl
Requires-Dist: scipy
Requires-Dist: parselmouth
